{
  "doc_id": "doc_018",
  "source_filename": "doc_018.pdf",
  "source_format": "pdf",
  "parsed_at": "2026-04-06T22:18:25.649251Z",
  "parser_version": "0.1.0",
  "total_pages": 6,
  "blocks": [
    {
      "block_id": "doc_018_tbl_001",
      "type": "table",
      "page": 1,
      "page_end": 2,
      "caption": null,
      "col_count": 17,
      "rows": [
        {
          "row_type": "header",
          "cells": [
            "",
            "",
            "Перечень монтажных единиц 98",
            "",
            "",
            "",
            "",
            "",
            "",
            "",
            "",
            "",
            "",
            "",
            "",
            "",
            ""
          ]
        },
        {
          "row_type": "data",
          "cells": [
            "",
            "",
            "Наименование",
            "",
            "",
            "",
            "",
            "ТН-1 10 Т-21 (60BAA21 GT121)",
            "",
            "",
            "ТН-2 10 Т-21 (60BAA21 GT221)",
            "Положение в АСУ ТП",
            "Цепи ТТ ТСН",
            "",
            "",
            "Цепи освещения",
            ""
          ]
        },
        {
          "row_type": "section",
          "cells": [
            "",
            "",
            "Обозначение",
            "",
            "",
            "",
            "",
            "",
            "",
            "",
            "",
            "",
            "",
            "",
            "",
            "",
            ""
          ]
        },
        {
          "row_type": "data",
          "cells": [
            "",
            "",
            "Номер монтажной единицы",
            "",
            "",
            "",
            "",
            "01",
            "",
            "",
            "02",
            "03",
            "04",
            "",
            "",
            "00",
            ""
          ]
        },
        {
          "row_type": "section",
          "cells": [
            "",
            "",
            "Примечания: 1.По данному чертежу изготовить один навесной шкаф размерами 1200х600х400. 2.Климатическое исполнение шкафа УХЛ4. 3.Конструкция шкафа должна обеспечивать защиту размещенных в нем аппаратов со степенью не хуже IP54. 4.Сейсмостойкость шкафа по шкале MSK-64 - 9 баллов 5.Металлоконструкция шкафа должна иметь порошковое покрытие светло-серого цвета RAL7035. 6.Подвод контрольных кабелей к шкафу осуществляется снизу. 7.В днище шкафа предусмотреть ступенчатые кабельные вводы для подвода кабелей. 8.В конструкции шкафа в качестве планки для ЭМС зажимов предусмотреть скобу - гребенку, с возможностью крепления кабелей с помощью экранирующих ЭМС и кабельных зажимов. Экранирующие зажимы ЭМС и кабельные зажимы должны входить в комплектацию шкафа. 9.Цепи освещения уточняются заводом-изготовителем. Евророзетка двойная, закрытая с заземлением. 10.Шкаф должен иметь информационную табличку на двери во всю ширину шкафа. Табличка выполняется из самоклеющейся бумаги с защитной пленкой или из тонкого пластика. Надпись выполняется шрифтом Arial с высотой букв 35 мм. Перед началом производства таблички произвести согласование макетов и материала с Заказчиком. 11.Под каждым аппаратом с лицевой стороны шкафа, а также под аппаратами, расположенными внутри шкафа, должны быть предусмотрены карманы маркировочные для соответствующего текста надписи 13.Для заземления резервных жил вторичных цепей, должны быть предусмотрены шинки вдоль боковин, соединенные с корпусом шкафа, либо клеммный ряд для заземления. 14.В нижней части шкафа предусмотреть медную шину для заземления всех нетоковедущих частей шкафа. 15.Выполнить подключение металлических частей шкафа заземляющим желто-зеленым проводником к шине заземления шкафа. 16.Указать место присоединения внешнего заземляющего устройства к корпусу шкафа. 17.Наклеить знаки \"Заземление\" около болтов и шины заземления, знак \"Осторожно электрическое напряжение\" наклеить на передней и задней дверях шкафа. 18.Монтаж внутри шкафа должен быть выполнен проводом с медной жилой и ПВХ изоляцией белого цвета с низким газо-и дымовыделением, не поддерживающим горение. 19.Монтаж в шкафу выполнить проводом сечением не менее 1,5 кв.мм для цепей тока, цепей напряжения, в цепях освещения и питания розеток шкафа и сечением 1 кв.мм для остальных цепей. 20.В шкафу предусмотреть короба для укладки проводов и для укладки жил кабелей рядом с клеммными зажимами, в объеме достаточном для укладки всех жил кабелей. 21.Двери шкафа должны закрываться стандартным замком (с двойной бороздкой). 22.Тип, количество зажимов и принадлежностей к клеммным зажимам определяет завод изготовитель из номенклатуры производителя клеммных зажимов. 23.Шкаф должен соответствовать требованиям, изложенные в Типовых проектных решениях ПАО \"Русгидро\" № 87-07-2015-РЗА.ТПР1.1 2024г 24.Укомплектовать ЗИП на гарантийный период",
            "",
            "",
            "",
            "",
            "",
            "",
            "",
            "",
            "",
            "",
            "",
            "",
            "",
            ""
          ]
        },
        {
          "row_type": "section",
          "cells": [
            "",
            "",
            "",
            "",
            "",
            "",
            "",
            "",
            "",
            "",
            "",
            "",
            "",
            "",
            "",
            "",
            ""
          ]
        },
        {
          "row_type": "section",
          "cells": [
            "",
            "",
            "",
            "",
            "",
            "",
            "",
            "",
            "",
            "",
            "",
            "",
            "",
            "",
            "",
            "",
            ""
          ]
        },
        {
          "row_type": "section",
          "cells": [
            "",
            "",
            "",
            "",
            "",
            "",
            "",
            "",
            "",
            "2261-26-102",
            "",
            "",
            "",
            "",
            "",
            "",
            ""
          ]
        },
        {
          "row_type": "section",
          "cells": [
            "",
            "",
            "",
            "",
            "",
            "",
            "",
            "",
            "",
            "",
            "",
            "",
            "",
            "",
            "",
            "",
            ""
          ]
        },
        {
          "row_type": "section",
          "cells": [
            "",
            "",
            "",
            "",
            "",
            "",
            "",
            "",
            "",
            "Реконструкция ОП \"Южно-Сахалинская ТЭЦ-1\" путем строительства 6-го энергоблока мощностью 50 МВт с установкой двух газотурбинных энергоагрегатов ЭГЭС-25ПА",
            "",
            "",
            "",
            "",
            "",
            "",
            ""
          ]
        },
        {
          "row_type": "section",
          "cells": [
            "",
            "",
            "",
            "",
            "",
            "",
            "",
            "",
            "",
            "",
            "",
            "",
            "",
            "",
            "",
            "",
            ""
          ]
        },
        {
          "row_type": "data",
          "cells": [
            "",
            "",
            "Изм.",
            "Кол.уч.",
            "Лист",
            "N док.",
            "Подпись",
            "",
            "Дата",
            "",
            "",
            "",
            "",
            "",
            "",
            "",
            ""
          ]
        },
        {
          "row_type": "data",
          "cells": [
            "",
            "",
            "Разработал",
            "",
            "Смирнова",
            "",
            "",
            "",
            "",
            "Задание заводу-изготовителю на шкаф зажимов ТН и ТТ",
            "",
            "",
            "",
            "Стадия",
            "Лист",
            "",
            "Листов"
          ]
        },
        {
          "row_type": "data",
          "cells": [
            "",
            "",
            "Проверил",
            "",
            "Обысова",
            "",
            "",
            "",
            "",
            "",
            "",
            "",
            "",
            "Р",
            "1",
            "",
            "6"
          ]
        },
        {
          "row_type": "section",
          "cells": [
            "",
            "",
            "",
            "",
            "",
            "",
            "",
            "",
            "",
            "",
            "",
            "",
            "",
            "",
            "",
            "",
            ""
          ]
        },
        {
          "row_type": "section",
          "cells": [
            "",
            "",
            "",
            "",
            "",
            "",
            "",
            "",
            "",
            "Шкаф зажимов ТН и ТТ (60BAA21 GH01)",
            "",
            "",
            "",
            "",
            "",
            "",
            ""
          ]
        },
        {
          "row_type": "section",
          "cells": [
            "",
            "",
            "Н.контроль",
            "",
            "Габышева",
            "",
            "",
            "",
            "",
            "",
            "",
            "",
            "",
            "",
            "",
            "",
            ""
          ]
        },
        {
          "row_type": "section",
          "cells": [
            "",
            "",
            "Нач.отд",
            "",
            "Грибанов",
            "",
            "",
            "",
            "",
            "",
            "",
            "",
            "",
            "",
            "",
            "",
            ""
          ]
        }
      ],
      "section_path": null,
      "xlsx_ref": "tables/doc_018_tbl_001.xlsx"
    },
    {
      "block_id": "doc_018_tbl_002",
      "type": "table",
      "page": 2,
      "page_end": 2,
      "caption": null,
      "col_count": 9,
      "rows": [
        {
          "row_type": "header",
          "cells": [
            "99 Вид спереди с дверью Вид спереди со снятой дверью Вид сбоку Пломбирование цепей учета SQ1 EL1 R1 03 01 X3 X01 10 кл. 8 кл. R2-R5 06х06 06х06 04 01 X4 X01 бороК 06х06 бороК 18 кл. бороК 00 X00 10 кл. 00SF1 42 кл. S1 SF1 01 X1 S2 SF1SF2SF3 21 кл. 02 S3 SF4 X2 15 кл. A A Короб 25х40 PE PE A-A Информационная табличка Дно шкафа. Подводка кабелей через сальники PG16, PG21 2 шт. Шкаф зажимов ТН и ТТ 60BAA21 GH01 Общий вид Лист 2261-26-102 2 Изм. Кол.уч. Лист N°док. Подпись Дата",
            "",
            "",
            "",
            "",
            "",
            "",
            "",
            ""
          ]
        },
        {
          "row_type": "section",
          "cells": [
            "",
            "",
            "",
            "",
            "",
            "",
            "",
            "2261-26-102",
            "Лист"
          ]
        },
        {
          "row_type": "section",
          "cells": [
            "",
            "",
            "",
            "",
            "",
            "",
            "",
            "",
            "2"
          ]
        },
        {
          "row_type": "data",
          "cells": [
            "",
            "Изм.",
            "Кол.уч.",
            "Лист",
            "N°до",
            "к. Подпись",
            "Дата",
            "",
            ""
          ]
        }
      ],
      "section_path": null,
      "xlsx_ref": "tables/doc_018_tbl_002.xlsx"
    },
    {
      "block_id": "doc_018_tbl_003",
      "type": "table",
      "page": 2,
      "page_end": 2,
      "caption": null,
      "col_count": 7,
      "rows": [
        {
          "row_type": "header",
          "cells": [
            "",
            "10 кл. 06х06 06х06 04 X4 бороК бороК 18 кл. 00 X00 10 кл. 00SF1 S1 SF1 S2 SF1SF2 S3 SF4",
            "SF3 2",
            "8 кл. 01 X01 42 кл 01 X1 1 кл 02 X2",
            ". .",
            "R2-R5 06х06 бороК",
            ""
          ]
        }
      ],
      "section_path": null,
      "xlsx_ref": "tables/doc_018_tbl_003.xlsx"
    },
    {
      "block_id": "doc_018_tbl_004",
      "type": "table",
      "page": 2,
      "page_end": 2,
      "caption": null,
      "col_count": 2,
      "rows": [
        {
          "row_type": "header",
          "cells": [
            "",
            ""
          ]
        },
        {
          "row_type": "data",
          "cells": [
            "PE",
            ""
          ]
        },
        {
          "row_type": "data",
          "cells": [
            "Шкаф зажимов ТН и ТТ",
            "60BAA21 GH01"
          ]
        }
      ],
      "section_path": null,
      "xlsx_ref": "tables/doc_018_tbl_004.xlsx"
    },
    {
      "block_id": "doc_018_b005",
      "type": "text",
      "page": 2,
      "content": "Формат А3",
      "heading_level": null,
      "section_path": null
    },
    {
      "block_id": "doc_018_tbl_005",
      "type": "table",
      "page": 3,
      "page_end": 3,
      "caption": null,
      "col_count": 9,
      "rows": [
        {
          "row_type": "header",
          "cells": [
            "Шкаф зажимов ТТ и ТН (60BAA21 GH01) 100 Монтажная единица 01 Цепи напряжения от Пломбирование ТН-1 10 Т-21 (60BAA21 GT121) цепей учета х1 а1 Uг, Y А X1 А Uг, Y N X1 1 60BAA21 А601.1 S1 SF1 60BAA21 А603.1 X01 X01 Y х1 а1 Uг, Y В 4 X1 60BAA21 B601.1 1 2 1 2 60BAA21 B602.1 1 2 100 B Uг, Y N X1 2 60BAA21 C601.1 3 4 60BAA21 C603.1 3 4 В; 0,2; 30 ВА √3 х1 а1 Uг, Y С 5 X1 60BAA21 N601.1 5 6 3 4 60BAA21 N603.1 5 6 C Uг, Y N X1 3 7 8 5 6 7 8 6 SF2 60BAA21 А603.2 X01 X01 1 2 60BAA21 B602.2 10 11 Цепи тока от 60BAA21 C603.2 12 13 ТТ-2 10 58T 3 4 60BAA21 N603.2 14 15 (60BAA10 GT412) (60BAA10 GT312) 16 17 3000/1 1000/1 5 6 -T4 A -T3 A 5PR20 30ВА 5PR20 30ВА SF3 60BAA21 А603.3 Л2 Л1 1 2 60BAA21 B602.2 19 20 И1 И2 И2 И1 -T4 B -T3 B 60BAA21 C603.3 21 22 3 4 60BAA21 N603.3 23 24 Л2 Л1 х2 а2 Uг, Y А X1 5 6 25 26 И2 И1 И2 И1 А S2 SF4 Uг, Y N X1 7 60BAA21 А601.2 60BAA21 А603.4 -T4 C -T3 C Y Л2 Л1 х2 а2 Uг, Y В 10 X1 60BAA21 B601.2 1 2 1 2 60BAA21 B602.2 28 29 100 Цепи освещения В; 0,5; 30 ВА B Uг, Y N X1 8 X1 60BAA21 C601.2 3 4 60BAA21 C603.4 √3 30 31 И2 И1 И2 И1 Монтажная единица 00 х2 а2 Uг, Y С 11 9 60BAA21 N601.2 5 6 3 4 60BAA21 N603.4 32 33 C Uг, Y N X1 7 8 5 6 34 35 4-118N 4-118A 4-118B 4-118C 3-118N 3-118A 3-118B 3-118C X00 12 РV1 1 А S3 SF5 хд ад Uг, Δ Н X1 60BAA21 H601.3 60BAA21 H603.3 X01 X01 V 4 Uг, Δ К X1 14 60BAA21 K601.3 1 2 1 2 60BAA21 K602.3 37 38 39 X1 15 60BAA21 F601.3 3 4 60BAA21 F603.3 41 42 R1 B 2 Δ хд ад Uг, Δ F X1 16 60BAA21 U601.3 5 6 3 4 60BAA21 U603.3 43 44 40 Монтажная единица 04 100 В; 3Р; 200 ВА Uг, Δ F X1 17 7 8 5 6 45 46 SB1 5 3 C 18 хд ад Uг, Δ И X1 -R5 X4 5 6 7 3 1 SF1 X4 14 15 16 ЕL1 Uг, Δ И 19 4 2 SQ1 X1 -R4 8 1 2 3 X4 17 10 11 12 11 12 1 2 20 -R3 -R2 XS1 Монтажная единица 02 Монтажная единица 03 Цепи напряжения от XS2 ТН-2 10 Т-21 хд ад 60BAA21 А601 Uг, Y А X2 60BAA21 А601 (60BAA21 GT221) А 60BAA21 N601 Uг, Y N X2 1 X3 SF1 X3 1 11 12 5 nтн_Y = U НОМ 3 ,Л 1 3 00 хд B ад 6 6 0 0 B B A A A A 2 2 1 1 B N 6 6 0 0 1 1 U U г г , , Y Y В N X2 4 X2 2 60BAA21 B601 SF2 хд ад 60BAA21 C601 Uг, Y С 5 X2 11 12 U Y C 60BAA21 N601 Uг, Y N X2 3 SF3 6 11 12 А SF4 X3 X3 х а 60BAA21 Н601 Uг, Δ Н X2 60BAA21 H601 11 12 2 6 60BAA21 К601 Uг, Δ К X2 8 60BAA21 K601 9 nтн_Δ = U НОМ 3 ,Л 1 3 00 х B а 60BAA21 Ф601 Uг, Δ F X X 2 2 10 X3 SF5 X3 3 11 12 7 60BAA21 Ф601 11 Uг, Δ F U X2 Схема электрическая полная C 12 х а 60BAA21 И601 Uг, Δ И X2 60BAA21 И601 Uг, Δ И X2 13 Лист 14 2261-26-102 3 Изм. Кол.уч. Лист N°док. Подпись Дата",
            "",
            "",
            "",
            "",
            "",
            "",
            "",
            ""
          ]
        },
        {
          "row_type": "section",
          "cells": [
            "",
            "",
            "",
            "",
            "",
            "",
            "",
            "2261-26-102",
            "Лист"
          ]
        },
        {
          "row_type": "section",
          "cells": [
            "",
            "",
            "",
            "",
            "",
            "",
            "",
            "",
            "3"
          ]
        },
        {
          "row_type": "data",
          "cells": [
            "",
            "Изм.",
            "Кол.уч.",
            "Лист",
            "N°док.",
            "Подпись",
            "Дата",
            "",
            ""
          ]
        }
      ],
      "section_path": null,
      "xlsx_ref": "tables/doc_018_tbl_005.xlsx"
    },
    {
      "block_id": "doc_018_tbl_006",
      "type": "table",
      "page": 3,
      "page_end": 3,
      "caption": null,
      "col_count": 3,
      "rows": [
        {
          "row_type": "header",
          "cells": [
            "",
            "",
            ""
          ]
        },
        {
          "row_type": "data",
          "cells": [
            "",
            "",
            ""
          ]
        },
        {
          "row_type": "data",
          "cells": [
            "",
            "",
            ""
          ]
        },
        {
          "row_type": "data",
          "cells": [
            "",
            "",
            ""
          ]
        },
        {
          "row_type": "data",
          "cells": [
            "",
            "",
            ""
          ]
        }
      ],
      "section_path": null,
      "xlsx_ref": "tables/doc_018_tbl_006.xlsx"
    },
    {
      "block_id": "doc_018_tbl_007",
      "type": "table",
      "page": 3,
      "page_end": 3,
      "caption": null,
      "col_count": 9,
      "rows": [
        {
          "row_type": "header",
          "cells": [
            "И1",
            "И2 -T4 B",
            "",
            "",
            "И1",
            "",
            "",
            "",
            ""
          ]
        },
        {
          "row_type": "data",
          "cells": [
            "",
            "И2",
            "И1",
            "-T4 C",
            "",
            "И2",
            "И1",
            "",
            ""
          ]
        },
        {
          "row_type": "data",
          "cells": [
            "4-118A",
            "",
            "4-118B",
            "И2",
            "3-118A",
            "",
            "3-118B",
            "И2",
            "И1 3-118C"
          ]
        },
        {
          "row_type": "data",
          "cells": [
            "5",
            "",
            "6",
            "",
            "14",
            "",
            "15",
            "",
            ""
          ]
        }
      ],
      "section_path": null,
      "xlsx_ref": "tables/doc_018_tbl_007.xlsx"
    },
    {
      "block_id": "doc_018_tbl_008",
      "type": "table",
      "page": 3,
      "page_end": 3,
      "caption": null,
      "col_count": 1,
      "rows": [
        {
          "row_type": "header",
          "cells": [
            ""
          ]
        },
        {
          "row_type": "data",
          "cells": [
            ""
          ]
        },
        {
          "row_type": "data",
          "cells": [
            ""
          ]
        },
        {
          "row_type": "data",
          "cells": [
            ""
          ]
        }
      ],
      "section_path": null,
      "xlsx_ref": "tables/doc_018_tbl_008.xlsx"
    },
    {
      "block_id": "doc_018_b010",
      "type": "text",
      "page": 3,
      "content": "Формат А4x3",
      "heading_level": null,
      "section_path": null
    },
    {
      "block_id": "doc_018_b011",
      "type": "text",
      "page": 4,
      "content": "Лист\n2261-26-102\n4\nИзм. Кол.уч. Лист N°док. Подпись Дата\nФормат А3\nеинаворибмолП\nатечу\nйепец\n101\nСхема электрическая соединений рядов зажимов",
      "heading_level": null,
      "section_path": null
    },
    {
      "block_id": "doc_018_tbl_009",
      "type": "table",
      "page": 4,
      "page_end": 4,
      "caption": null,
      "col_count": 9,
      "rows": [
        {
          "row_type": "header",
          "cells": [
            "",
            "",
            "",
            "",
            "",
            "",
            "",
            "",
            ""
          ]
        },
        {
          "row_type": "section",
          "cells": [
            "",
            "",
            "",
            "",
            "",
            "",
            "",
            "",
            ""
          ]
        },
        {
          "row_type": "section",
          "cells": [
            "",
            "",
            "",
            "",
            "",
            "",
            "",
            "",
            ""
          ]
        },
        {
          "row_type": "section",
          "cells": [
            "",
            "",
            "",
            "",
            "",
            "",
            "",
            "",
            ""
          ]
        },
        {
          "row_type": "section",
          "cells": [
            "",
            "",
            "",
            "",
            "",
            "",
            "",
            "",
            ""
          ]
        },
        {
          "row_type": "section",
          "cells": [
            "",
            "",
            "",
            "",
            "",
            "",
            "",
            "",
            ""
          ]
        },
        {
          "row_type": "section",
          "cells": [
            "",
            "",
            "",
            "",
            "",
            "",
            "",
            "",
            ""
          ]
        },
        {
          "row_type": "section",
          "cells": [
            "",
            "",
            "",
            "",
            "",
            "",
            "",
            "",
            ""
          ]
        },
        {
          "row_type": "section",
          "cells": [
            "",
            "",
            "",
            "",
            "",
            "",
            "",
            "",
            ""
          ]
        },
        {
          "row_type": "section",
          "cells": [
            "",
            "",
            "",
            "",
            "",
            "",
            "",
            "",
            ""
          ]
        },
        {
          "row_type": "section",
          "cells": [
            "",
            "",
            "",
            "",
            "",
            "",
            "",
            "",
            ""
          ]
        },
        {
          "row_type": "section",
          "cells": [
            "",
            "",
            "",
            "",
            "",
            "",
            "",
            "",
            ""
          ]
        },
        {
          "row_type": "section",
          "cells": [
            "",
            "",
            "",
            "",
            "",
            "",
            "",
            "",
            ""
          ]
        },
        {
          "row_type": "section",
          "cells": [
            "",
            "",
            "",
            "",
            "",
            "",
            "",
            "",
            ""
          ]
        },
        {
          "row_type": "section",
          "cells": [
            "",
            "",
            "",
            "",
            "",
            "",
            "",
            "",
            ""
          ]
        },
        {
          "row_type": "section",
          "cells": [
            "",
            "",
            "",
            "",
            "",
            "",
            "",
            "",
            ""
          ]
        },
        {
          "row_type": "section",
          "cells": [
            "",
            "",
            "",
            "",
            "",
            "",
            "",
            "",
            ""
          ]
        },
        {
          "row_type": "section",
          "cells": [
            "",
            "",
            "",
            "",
            "",
            "",
            "",
            "",
            ""
          ]
        },
        {
          "row_type": "section",
          "cells": [
            "",
            "",
            "",
            "",
            "",
            "",
            "",
            "",
            ""
          ]
        }
      ],
      "section_path": null,
      "xlsx_ref": "tables/doc_018_tbl_009.xlsx"
    },
    {
      "block_id": "doc_018_tbl_010",
      "type": "table",
      "page": 4,
      "page_end": 4,
      "caption": null,
      "col_count": 50,
      "rows": [
        {
          "row_type": "header",
          "cells": [
            "",
            "",
            "",
            "",
            "",
            "",
            "",
            "",
            "",
            "",
            "",
            "",
            "",
            "",
            "",
            "",
            "",
            "",
            "",
            "",
            "",
            "",
            "",
            "",
            "",
            "",
            "",
            "",
            "",
            "",
            "",
            "",
            "",
            "",
            "",
            "",
            "",
            "",
            "",
            "",
            "",
            "",
            "",
            "",
            "",
            "",
            "",
            "",
            "",
            ""
          ]
        },
        {
          "row_type": "data",
          "cells": [
            "",
            "1.306А 12AAB06",
            "",
            "1.206B 12AAB06",
            "",
            "1.306C 12AAB06",
            "",
            "1.306N 12AAB06",
            "",
            "",
            "",
            "",
            "",
            "",
            "",
            "",
            "",
            "",
            "",
            "3.306А 12AAB06",
            "",
            "2.206B 12AAB06",
            "3.306C 12AAB06",
            "",
            "3.306N 12AAB06",
            "",
            "",
            "4.306А 12AAB06",
            "",
            "",
            "2.206B 12AAB06",
            "",
            "4.306C 12AAB06",
            "4.306N 12AAB06",
            "",
            "",
            "3.306H 12AAB06",
            "",
            "",
            "",
            "3.206K 12AAB06",
            "",
            "",
            "3.306F 12AAB06",
            "3.306U 12AAB06",
            "",
            "",
            "",
            "",
            ""
          ]
        },
        {
          "row_type": "section",
          "cells": [
            "",
            "",
            "",
            "",
            "",
            "",
            "",
            "",
            "",
            "",
            "",
            "",
            "",
            "",
            "",
            "",
            "",
            "",
            "",
            "",
            "",
            "",
            "",
            "",
            "",
            "",
            "",
            "",
            "",
            "",
            "",
            "",
            "",
            "",
            "",
            "",
            "",
            "",
            "",
            "",
            "",
            "",
            "",
            "",
            "",
            "",
            "",
            "",
            "",
            ""
          ]
        },
        {
          "row_type": "section",
          "cells": [
            "",
            "",
            "",
            "",
            "",
            "",
            "",
            "",
            "",
            "",
            "",
            "",
            "",
            "",
            "",
            "",
            "",
            "",
            "",
            "",
            "",
            "",
            "",
            "",
            "",
            "",
            "",
            "",
            "",
            "",
            "",
            "",
            "",
            "",
            "",
            "",
            "",
            "",
            "",
            "",
            "",
            "",
            "",
            "",
            "",
            "",
            "",
            "",
            "",
            ""
          ]
        },
        {
          "row_type": "section",
          "cells": [
            "",
            "",
            "",
            "",
            "",
            "",
            "",
            "",
            "",
            "",
            "",
            "",
            "",
            "",
            "",
            "",
            "",
            "",
            "",
            "",
            "",
            "",
            "",
            "",
            "",
            "",
            "",
            "",
            "",
            "",
            "",
            "",
            "",
            "",
            "",
            "",
            "",
            "",
            "",
            "",
            "",
            "",
            "",
            "",
            "",
            "",
            "",
            "",
            "",
            ""
          ]
        },
        {
          "row_type": "section",
          "cells": [
            "",
            "",
            "",
            "",
            "",
            "",
            "",
            "",
            "",
            "",
            "",
            "",
            "",
            "",
            "",
            "",
            "",
            "",
            "",
            "",
            "",
            "",
            "",
            "",
            "",
            "",
            "",
            "",
            "",
            "",
            "",
            "",
            "",
            "",
            "",
            "",
            "",
            "",
            "",
            "",
            "",
            "",
            "",
            "",
            "",
            "",
            "",
            "",
            "",
            ""
          ]
        },
        {
          "row_type": "section",
          "cells": [
            "",
            "",
            "",
            "",
            "",
            "",
            "",
            "",
            "",
            "",
            "",
            "",
            "",
            "",
            "",
            "",
            "",
            "",
            "",
            "",
            "",
            "",
            "",
            "",
            "",
            "",
            "",
            "",
            "",
            "",
            "",
            "",
            "",
            "",
            "",
            "",
            "",
            "",
            "",
            "",
            "",
            "",
            "",
            "",
            "",
            "",
            "",
            "",
            "",
            ""
          ]
        },
        {
          "row_type": "section",
          "cells": [
            "",
            "",
            "",
            "",
            "",
            "",
            "",
            "",
            "",
            "",
            "",
            "",
            "",
            "",
            "",
            "",
            "",
            "",
            "",
            "",
            "",
            "",
            "",
            "",
            "",
            "",
            "",
            "",
            "",
            "",
            "",
            "",
            "",
            "",
            "",
            "",
            "",
            "",
            "",
            "",
            "",
            "",
            "",
            "",
            "",
            "",
            "",
            "",
            "",
            ""
          ]
        }
      ],
      "section_path": null,
      "xlsx_ref": "tables/doc_018_tbl_010.xlsx"
    },
    {
      "block_id": "doc_018_tbl_011",
      "type": "table",
      "page": 4,
      "page_end": 4,
      "caption": null,
      "col_count": 8,
      "rows": [
        {
          "row_type": "header",
          "cells": [
            "",
            "",
            "",
            "",
            "",
            "",
            "",
            ""
          ]
        },
        {
          "row_type": "section",
          "cells": [
            "",
            "",
            "",
            "",
            "",
            "",
            "",
            ""
          ]
        },
        {
          "row_type": "section",
          "cells": [
            "",
            "",
            "",
            "",
            "",
            "",
            "",
            ""
          ]
        },
        {
          "row_type": "section",
          "cells": [
            "",
            "",
            "",
            "",
            "",
            "",
            "",
            ""
          ]
        },
        {
          "row_type": "section",
          "cells": [
            "",
            "",
            "",
            "",
            "",
            "",
            "",
            ""
          ]
        },
        {
          "row_type": "section",
          "cells": [
            "",
            "",
            "",
            "",
            "",
            "",
            "",
            ""
          ]
        },
        {
          "row_type": "section",
          "cells": [
            "",
            "",
            "",
            "",
            "",
            "",
            "",
            ""
          ]
        },
        {
          "row_type": "section",
          "cells": [
            "",
            "",
            "",
            "",
            "",
            "",
            "",
            ""
          ]
        },
        {
          "row_type": "section",
          "cells": [
            "",
            "",
            "",
            "",
            "",
            "",
            "",
            ""
          ]
        },
        {
          "row_type": "section",
          "cells": [
            "",
            "",
            "",
            "",
            "",
            "",
            "",
            ""
          ]
        },
        {
          "row_type": "section",
          "cells": [
            "",
            "",
            "",
            "",
            "",
            "",
            "",
            ""
          ]
        },
        {
          "row_type": "section",
          "cells": [
            "",
            "",
            "",
            "",
            "",
            "",
            "",
            ""
          ]
        },
        {
          "row_type": "section",
          "cells": [
            "",
            "",
            "",
            "",
            "",
            "",
            "",
            ""
          ]
        }
      ],
      "section_path": null,
      "xlsx_ref": "tables/doc_018_tbl_011.xlsx"
    },
    {
      "block_id": "doc_018_tbl_012",
      "type": "table",
      "page": 4,
      "page_end": 4,
      "caption": null,
      "col_count": 12,
      "rows": [
        {
          "row_type": "header",
          "cells": [
            "",
            "",
            "",
            "",
            "",
            "",
            "",
            "",
            "",
            "",
            "",
            ""
          ]
        },
        {
          "row_type": "section",
          "cells": [
            "",
            "",
            "",
            "",
            "",
            "",
            "",
            "",
            "",
            "",
            "",
            ""
          ]
        },
        {
          "row_type": "section",
          "cells": [
            "",
            "",
            "",
            "",
            "",
            "",
            "",
            "",
            "",
            "",
            "",
            ""
          ]
        },
        {
          "row_type": "section",
          "cells": [
            "",
            "",
            "",
            "",
            "",
            "",
            "",
            "",
            "",
            "",
            "",
            ""
          ]
        },
        {
          "row_type": "section",
          "cells": [
            "",
            "",
            "",
            "",
            "",
            "",
            "",
            "",
            "",
            "",
            "",
            ""
          ]
        },
        {
          "row_type": "section",
          "cells": [
            "",
            "",
            "",
            "",
            "",
            "",
            "",
            "",
            "",
            "",
            "",
            ""
          ]
        }
      ],
      "section_path": null,
      "xlsx_ref": "tables/doc_018_tbl_012.xlsx"
    },
    {
      "block_id": "doc_018_tbl_013",
      "type": "table",
      "page": 4,
      "page_end": 4,
      "caption": null,
      "col_count": 19,
      "rows": [
        {
          "row_type": "header",
          "cells": [
            "",
            "",
            "",
            "",
            "",
            "",
            "",
            "",
            "",
            "",
            "",
            "",
            "",
            "",
            "",
            "",
            "",
            "",
            ""
          ]
        },
        {
          "row_type": "section",
          "cells": [
            "",
            "",
            "",
            "",
            "",
            "",
            "",
            "",
            "",
            "",
            "",
            "",
            "",
            "",
            "",
            "",
            "",
            "",
            ""
          ]
        },
        {
          "row_type": "section",
          "cells": [
            "",
            "",
            "",
            "",
            "",
            "",
            "",
            "",
            "",
            "",
            "",
            "",
            "",
            "",
            "",
            "",
            "",
            "",
            ""
          ]
        },
        {
          "row_type": "section",
          "cells": [
            "",
            "",
            "",
            "",
            "",
            "",
            "",
            "",
            "",
            "",
            "",
            "",
            "",
            "",
            "",
            "",
            "",
            "",
            ""
          ]
        }
      ],
      "section_path": null,
      "xlsx_ref": "tables/doc_018_tbl_013.xlsx"
    },
    {
      "block_id": "doc_018_tbl_014",
      "type": "table",
      "page": 4,
      "page_end": 4,
      "caption": null,
      "col_count": 10,
      "rows": [
        {
          "row_type": "header",
          "cells": [
            "",
            "",
            "",
            "",
            "",
            "",
            "",
            "",
            "",
            ""
          ]
        },
        {
          "row_type": "section",
          "cells": [
            "",
            "",
            "",
            "",
            "",
            "",
            "",
            "",
            "",
            ""
          ]
        },
        {
          "row_type": "section",
          "cells": [
            "",
            "",
            "",
            "",
            "",
            "",
            "",
            "",
            "",
            ""
          ]
        },
        {
          "row_type": "section",
          "cells": [
            "",
            "",
            "",
            "",
            "",
            "",
            "",
            "",
            "",
            ""
          ]
        }
      ],
      "section_path": null,
      "xlsx_ref": "tables/doc_018_tbl_014.xlsx"
    },
    {
      "block_id": "doc_018_tbl_015",
      "type": "table",
      "page": 4,
      "page_end": 4,
      "caption": null,
      "col_count": 2,
      "rows": [
        {
          "row_type": "header",
          "cells": [
            "",
            ""
          ]
        },
        {
          "row_type": "data",
          "cells": [
            "",
            ""
          ]
        },
        {
          "row_type": "data",
          "cells": [
            "",
            ""
          ]
        }
      ],
      "section_path": null,
      "xlsx_ref": "tables/doc_018_tbl_015.xlsx"
    },
    {
      "block_id": "doc_018_tbl_016",
      "type": "table",
      "page": 4,
      "page_end": 5,
      "caption": null,
      "col_count": 6,
      "rows": [
        {
          "row_type": "header",
          "cells": [
            "",
            "",
            "",
            "",
            "",
            ""
          ]
        },
        {
          "row_type": "section",
          "cells": [
            "",
            "",
            "",
            "",
            "",
            ""
          ]
        }
      ],
      "section_path": null,
      "xlsx_ref": "tables/doc_018_tbl_016.xlsx"
    },
    {
      "block_id": "doc_018_tbl_017",
      "type": "table",
      "page": 5,
      "page_end": 6,
      "caption": null,
      "col_count": 12,
      "rows": [
        {
          "row_type": "header",
          "cells": [
            "",
            "",
            "102 Перечень надписей",
            "",
            "",
            "",
            "",
            "",
            "",
            "",
            "",
            ""
          ]
        },
        {
          "row_type": "data",
          "cells": [
            "",
            "",
            "Поз.",
            "",
            "",
            "Место надписи",
            "",
            "",
            "",
            "Текст надписи",
            "Примечание",
            ""
          ]
        },
        {
          "row_type": "section",
          "cells": [
            "",
            "",
            "",
            "",
            "",
            "",
            "",
            "",
            "",
            "",
            "",
            ""
          ]
        },
        {
          "row_type": "data",
          "cells": [
            "",
            "",
            "SB1",
            "",
            "",
            "в рамке",
            "",
            "",
            "",
            "Напраяжение небаланса ТН-3 10 Т21 10,5кВ /Замер небаланса 3Uo",
            "",
            ""
          ]
        },
        {
          "row_type": "data",
          "cells": [
            "",
            "",
            "PV1",
            "",
            "",
            "в рамке",
            "",
            "",
            "",
            "Напраяжение небаланса ТН-3 10 Т21 10,5кВ /Замер небаланса 3Uo",
            "",
            ""
          ]
        },
        {
          "row_type": "section",
          "cells": [
            "",
            "",
            "",
            "",
            "",
            "",
            "",
            "",
            "",
            "",
            "",
            ""
          ]
        },
        {
          "row_type": "data",
          "cells": [
            "",
            "",
            "S1",
            "",
            "",
            "в рамке",
            "",
            "",
            "",
            "цепи переменного напряжения \"звезды\" ТН-3 10 Т21 АИИСКУЭ",
            "",
            ""
          ]
        },
        {
          "row_type": "data",
          "cells": [
            "",
            "",
            "S2",
            "",
            "",
            "в рамке",
            "",
            "",
            "",
            "цепи переменного напряжения \"звезды\" ТН-3 10 Т21",
            "",
            ""
          ]
        },
        {
          "row_type": "data",
          "cells": [
            "",
            "",
            "S3",
            "",
            "",
            "в рамке",
            "",
            "",
            "",
            "цепи переменного напряжения \"треугольника\" ТН-3 10 Т21",
            "",
            ""
          ]
        },
        {
          "row_type": "section",
          "cells": [
            "",
            "",
            "",
            "",
            "",
            "",
            "",
            "",
            "",
            "",
            "",
            ""
          ]
        },
        {
          "row_type": "section",
          "cells": [
            "",
            "",
            "",
            "",
            "",
            "",
            "",
            "",
            "",
            "",
            "",
            ""
          ]
        },
        {
          "row_type": "section",
          "cells": [
            "",
            "",
            "",
            "",
            "",
            "",
            "",
            "",
            "",
            "",
            "",
            ""
          ]
        },
        {
          "row_type": "section",
          "cells": [
            "",
            "",
            "",
            "",
            "",
            "",
            "",
            "",
            "",
            "",
            "",
            ""
          ]
        },
        {
          "row_type": "section",
          "cells": [
            "",
            "",
            "",
            "",
            "",
            "",
            "",
            "",
            "",
            "",
            "",
            ""
          ]
        },
        {
          "row_type": "section",
          "cells": [
            "",
            "",
            "",
            "",
            "",
            "",
            "",
            "",
            "",
            "",
            "",
            ""
          ]
        },
        {
          "row_type": "section",
          "cells": [
            "",
            "",
            "",
            "",
            "",
            "",
            "",
            "",
            "",
            "",
            "",
            ""
          ]
        },
        {
          "row_type": "section",
          "cells": [
            "",
            "",
            "",
            "",
            "",
            "",
            "",
            "",
            "",
            "",
            "",
            ""
          ]
        },
        {
          "row_type": "section",
          "cells": [
            "",
            "",
            "",
            "",
            "",
            "",
            "",
            "",
            "",
            "",
            "",
            ""
          ]
        },
        {
          "row_type": "section",
          "cells": [
            "",
            "",
            "",
            "",
            "",
            "",
            "",
            "",
            "",
            "",
            "",
            ""
          ]
        },
        {
          "row_type": "section",
          "cells": [
            "",
            "",
            "",
            "",
            "",
            "",
            "",
            "",
            "",
            "2261-26-102",
            "",
            "Лист"
          ]
        },
        {
          "row_type": "section",
          "cells": [
            "",
            "",
            "",
            "",
            "",
            "",
            "",
            "",
            "",
            "",
            "",
            "5"
          ]
        },
        {
          "row_type": "data",
          "cells": [
            "",
            "",
            "Изм.",
            "Кол.уч.",
            "Лист",
            "",
            "N°док.",
            "Подпись",
            "Дата",
            "",
            "",
            ""
          ]
        }
      ],
      "section_path": null,
      "xlsx_ref": "tables/doc_018_tbl_017.xlsx"
    },
    {
      "block_id": "doc_018_tbl_018",
      "type": "table",
      "page": 6,
      "page_end": 6,
      "caption": null,
      "col_count": 14,
      "rows": [
        {
          "row_type": "header",
          "cells": [
            "",
            "",
            "103",
            "",
            "",
            "",
            "",
            "",
            "",
            "",
            "",
            "",
            "",
            ""
          ]
        },
        {
          "row_type": "data",
          "cells": [
            "",
            "",
            "Поз. обозн. и N монтаж. единицы",
            "",
            "Обозначение",
            "",
            "",
            "",
            "",
            "",
            "Наименование",
            "Кол.",
            "",
            ""
          ]
        },
        {
          "row_type": "data",
          "cells": [
            "",
            "",
            "",
            "",
            "",
            "",
            "",
            "",
            "",
            "",
            "Шкаф зажимов ТН и ТТ нетиповой",
            "1",
            "Габариты 1200х600х400",
            ""
          ]
        },
        {
          "row_type": "section",
          "cells": [
            "",
            "",
            "01 PV1",
            "",
            "",
            "",
            "",
            "",
            "",
            "",
            "Вольтметр",
            "",
            "",
            ""
          ]
        },
        {
          "row_type": "section",
          "cells": [
            "",
            "",
            "",
            "",
            "",
            "",
            "",
            "",
            "",
            "",
            "Э-365, шкала 0...150 В",
            "1",
            "",
            ""
          ]
        },
        {
          "row_type": "data",
          "cells": [
            "",
            "",
            "01 SB1",
            "",
            "",
            "",
            "",
            "",
            "",
            "",
            "Кнопка КЕ - 011 исп. 4",
            "1",
            "",
            ""
          ]
        },
        {
          "row_type": "data",
          "cells": [
            "",
            "",
            "01 R1",
            "",
            "",
            "",
            "",
            "",
            "",
            "",
            "Резистор ПЭВР-50 1500 Ом ± 10 %",
            "1",
            "",
            ""
          ]
        },
        {
          "row_type": "section",
          "cells": [
            "",
            "",
            "01 S1, S2,",
            "",
            "",
            "",
            "",
            "",
            "",
            "",
            "Рубильник 250В, Iн=16А",
            "",
            "",
            ""
          ]
        },
        {
          "row_type": "data",
          "cells": [
            "",
            "",
            "S3",
            "",
            "",
            "",
            "",
            "",
            "",
            "",
            "Р231111",
            "3",
            "",
            ""
          ]
        },
        {
          "row_type": "section",
          "cells": [
            "",
            "",
            "01 SF1,SF2,",
            "",
            "",
            "",
            "",
            "",
            "",
            "",
            "Автоматический выключатель",
            "",
            "",
            ""
          ]
        },
        {
          "row_type": "section",
          "cells": [
            "",
            "",
            "SF3,SF4,",
            "",
            "",
            "",
            "",
            "",
            "",
            "",
            "Iном=4A Iсраб=5-10Iном",
            "",
            "",
            ""
          ]
        },
        {
          "row_type": "data",
          "cells": [
            "",
            "",
            "SF5",
            "",
            "",
            "",
            "",
            "",
            "",
            "",
            "C60N C N 24347",
            "5",
            "",
            ""
          ]
        },
        {
          "row_type": "data",
          "cells": [
            "",
            "",
            "01 R2-R5",
            "",
            "",
            "",
            "",
            "",
            "",
            "",
            "Резистор 100 Вт, 100 Ом С5-35В",
            "4",
            "",
            ""
          ]
        },
        {
          "row_type": "section",
          "cells": [
            "",
            "",
            "00 SQ2",
            "",
            "",
            "",
            "",
            "",
            "",
            "",
            "Концевой выключатель двери",
            "",
            "",
            ""
          ]
        },
        {
          "row_type": "section",
          "cells": [
            "",
            "",
            "",
            "",
            "",
            "",
            "",
            "",
            "",
            "",
            "ВВП11-10Б 313 20У314",
            "1",
            "",
            ""
          ]
        },
        {
          "row_type": "section",
          "cells": [
            "",
            "",
            "00 XS1,XS2",
            "",
            "",
            "",
            "",
            "",
            "",
            "",
            "Розетка с заземляющим контактом,",
            "",
            "",
            ""
          ]
        },
        {
          "row_type": "section",
          "cells": [
            "",
            "",
            "",
            "",
            "",
            "",
            "",
            "",
            "",
            "",
            "16А, 250В, 50Гц Арт.: mdse-47-pro РДЕ",
            "2",
            "",
            ""
          ]
        },
        {
          "row_type": "section",
          "cells": [
            "",
            "",
            "00 EL1",
            "",
            "",
            "",
            "",
            "",
            "",
            "",
            "Светильник светодиодный щитовой",
            "",
            "",
            ""
          ]
        },
        {
          "row_type": "section",
          "cells": [
            "",
            "",
            "",
            "",
            "",
            "",
            "",
            "",
            "",
            "",
            "220В, 5Вт, магнит",
            "",
            "",
            ""
          ]
        },
        {
          "row_type": "section",
          "cells": [
            "",
            "",
            "",
            "",
            "",
            "",
            "",
            "",
            "",
            "",
            "ELM025 арт. ELM025",
            "1",
            "",
            ""
          ]
        },
        {
          "row_type": "section",
          "cells": [
            "",
            "",
            "00 SF1",
            "",
            "",
            "",
            "",
            "",
            "",
            "",
            "Выключатель автоматический 2P, 2A, C",
            "",
            "",
            ""
          ]
        },
        {
          "row_type": "section",
          "cells": [
            "",
            "",
            "",
            "",
            "",
            "",
            "",
            "",
            "",
            "",
            "BM63-2C2-УХЛ3 арт. 260603",
            "1",
            "",
            ""
          ]
        },
        {
          "row_type": "section",
          "cells": [
            "",
            "",
            "Х1, Х2,",
            "",
            "",
            "",
            "",
            "",
            "",
            "",
            "Измерительная клемма с ползунковым",
            "",
            "",
            ""
          ]
        },
        {
          "row_type": "data",
          "cells": [
            "",
            "",
            "X01",
            "",
            "",
            "",
            "",
            "",
            "",
            "",
            "размыкателем PTME 4",
            "86",
            "",
            ""
          ]
        },
        {
          "row_type": "section",
          "cells": [
            "",
            "",
            "X4",
            "",
            "",
            "",
            "",
            "",
            "",
            "",
            "Измерительная клемма с ползунковым",
            "",
            "",
            ""
          ]
        },
        {
          "row_type": "section",
          "cells": [
            "",
            "",
            "",
            "",
            "",
            "",
            "",
            "",
            "",
            "",
            "",
            "",
            "",
            ""
          ]
        },
        {
          "row_type": "section",
          "cells": [
            "",
            "",
            "",
            "",
            "",
            "",
            "",
            "",
            "",
            "",
            "размыкателем UT 6-T-HV",
            "18",
            "",
            ""
          ]
        },
        {
          "row_type": "section",
          "cells": [
            "",
            "",
            "X3, X00",
            "",
            "",
            "",
            "",
            "",
            "",
            "",
            "Измерительная клемма с ползунковым",
            "",
            "",
            ""
          ]
        },
        {
          "row_type": "section",
          "cells": [
            "",
            "",
            "",
            "",
            "",
            "",
            "",
            "",
            "",
            "",
            "размыкателем PTU 6-T-P",
            "18",
            "",
            ""
          ]
        },
        {
          "row_type": "section",
          "cells": [
            "",
            "",
            "",
            "",
            "",
            "",
            "",
            "",
            "",
            "",
            "",
            "",
            "",
            ""
          ]
        },
        {
          "row_type": "section",
          "cells": [
            "",
            "",
            "",
            "",
            "",
            "",
            "",
            "",
            "",
            "",
            "Скоба - гребенка ЦИ.745322.001",
            "2",
            "",
            ""
          ]
        },
        {
          "row_type": "section",
          "cells": [
            "",
            "",
            "",
            "",
            "",
            "",
            "",
            "",
            "",
            "",
            "Зажим ЭМС для экрана кабеля",
            "",
            "cм. лист 2",
            ""
          ]
        },
        {
          "row_type": "section",
          "cells": [
            "",
            "",
            "",
            "",
            "",
            "",
            "",
            "",
            "",
            "",
            "Кабельный зажим",
            "",
            "cм. лист 2",
            ""
          ]
        },
        {
          "row_type": "section",
          "cells": [
            "",
            "",
            "Таблица УК и технические данные аппаратуры по заказу",
            "",
            "",
            "",
            "",
            "",
            "",
            "",
            "",
            "",
            "",
            ""
          ]
        },
        {
          "row_type": "section",
          "cells": [
            "",
            "",
            "",
            "",
            "",
            "",
            "",
            "",
            "",
            "",
            "",
            "",
            "",
            ""
          ]
        },
        {
          "row_type": "section",
          "cells": [
            "",
            "",
            "",
            "",
            "",
            "",
            "",
            "",
            "",
            "2261-26-102",
            "",
            "",
            "",
            "Лист"
          ]
        },
        {
          "row_type": "section",
          "cells": [
            "",
            "",
            "",
            "",
            "",
            "",
            "",
            "",
            "",
            "",
            "",
            "",
            "",
            "6"
          ]
        },
        {
          "row_type": "data",
          "cells": [
            "",
            "",
            "Изм.",
            "Кол.уч.",
            "",
            "Лист",
            "N°док.",
            "Подпись",
            "Дата",
            "",
            "",
            "",
            "",
            ""
          ]
        }
      ],
      "section_path": null,
      "xlsx_ref": "tables/doc_018_tbl_018.xlsx"
    }
  ]
}