{
  "doc_id": "doc_011",
  "source_filename": "doc_011.pdf",
  "doc_type": "other",
  "title": "doc_011.pdf",
  "summary": "Документ содержит нечитаемый OCR-текст 'III 3111411' на первой странице и ссылку на изображение 'img-0.jpeg'. Содержимое не поддается анализу из-за низкого качества распознавания.",
  "sections": [
    {
      "section_id": "1",
      "title": "Страница 1",
      "summary": "Нечитаемый текст и изображение.",
      "key_entities": [
        "III 3111411",
        "img-0.jpeg"
      ]
    }
  ],
  "key_topics": [
    "Неопределенные"
  ],
  "key_entities": [
    "III 3111411",
    "img-0.jpeg"
  ],
  "text_blocks_count": 0,
  "tables_count": 0,
  "images_count": 1,
  "estimated_tokens": 19,
  "generated_at": "2026-04-06T22:09:30.886147Z"
}